cadenai/__init__.py
cadenai/chains/__init__.py
cadenai/chains/llm_chain.py
cadenai/chains/retrieval_chain.py
cadenai/document/__init__.py
cadenai/document/file_handler.py
cadenai/document/text_splitter.py
cadenai/encoder.py
cadenai/llm/__init__.py
cadenai/llm/chat_wrapper.py
cadenai/prompt_manager/prompt_list.py
cadenai/prompt_manager/template.py
cadenai/schema.py
cadenai/vectorization/embeddings.py
cadenai/vectorization/vector_db.py
cadenai-0.1.0.dist-info/METADATA
cadenai-0.1.0.dist-info/WHEEL
cadenai-0.1.0.dist-info/RECORD
